bacdiving/__init__.py
bacdiving/bacdive_caller.py
bacdiving/circulartree.py
bacdiving/treeplots_maker.py
bacdiving/visualizations_maker.py
bacdiving-1.2.7.dist-info/LICENSE
bacdiving-1.2.7.dist-info/METADATA
bacdiving-1.2.7.dist-info/WHEEL
bacdiving-1.2.7.dist-info/top_level.txt
bacdiving-1.2.7.dist-info/RECORD
